Silicon.srcs/sources_1/new/traffic_signal_fsm.v
module traffic_signal_fsm (
    input clk,
    input reset,                     // Hard reset → NORTH_GREEN
    input emergency_force_red,       // Force ALL RED + freeze timer (wrong-way ambulance)
    input emergency_green_north,     // Force NORTH GREEN
    input emergency_green_east,      // Force EAST GREEN
    input emergency_green_south,     // Force SOUTH GREEN
    input emergency_green_west,      // Force WEST GREEN
    input soft_reset,                // Resume from stored state after emergency
    output reg [1:0] north_light,
    output reg [1:0] east_light,
    output reg [1:0] west_light,
    output reg [1:0] south_light,
    output reg [6:0] timer,
    output reg emergency_active      // Indicates emergency mode is active
);

// Light encodings
parameter GREEN   = 2'b01;
parameter YELLOW  = 2'b10;
parameter RED     = 2'b00;
parameter ALL_RED = 2'b11;   // Pedestrian crossing

// FSM states (12 states: 4 directions × 3 phases)
parameter NORTH_GREEN  = 4'd0;
parameter NORTH_YELLOW = 4'd1;
parameter NORTH_RED    = 4'd2;   // ALL_RED pedestrian
parameter EAST_GREEN   = 4'd3;
parameter EAST_YELLOW  = 4'd4;
parameter EAST_RED     = 4'd5;   // ALL_RED pedestrian
parameter SOUTH_GREEN  = 4'd6;
parameter SOUTH_YELLOW = 4'd7;
parameter SOUTH_RED    = 4'd8;   // ALL_RED pedestrian
parameter WEST_GREEN   = 4'd9;
parameter WEST_YELLOW  = 4'd10;
parameter WEST_RED     = 4'd11;  // ALL_RED pedestrian

reg [3:0] current_state, next_state;
reg [6:0] count;
reg [6:0] count_next;

// Emergency storage registers
reg        emergency_mode;
reg [2:0]  emergency_type;        // 0=force_red, 1=north_green, 2=east_green, 3=south_green, 4=west_green
reg [3:0]  stored_state;
reg [6:0]  stored_count;
reg [6:0]  stored_count_next;

// Emergency priority: force_red > north > east > south > west
wire any_emergency = emergency_force_red || emergency_green_north || emergency_green_east ||
                     emergency_green_south || emergency_green_west;

always @(posedge clk or posedge reset) begin
    if (reset) begin  // HARD RESET - complete refresh
        current_state <= NORTH_GREEN;
        count <= 7'd0;
        emergency_mode <= 1'b0;
        stored_state <= NORTH_GREEN;
        stored_count <= 7'd0;
        stored_count_next <= 7'd0;
        emergency_type <= 3'd0;
    end else begin
        if (!emergency_mode && any_emergency) begin
            // ENTER EMERGENCY MODE - store current state and freeze everything
            emergency_mode <= 1'b1;
            stored_state <= current_state;
            stored_count <= count;
            stored_count_next <= count_next;
            
            // Determine emergency type (priority: force_red > north > east > south > west)
            if (emergency_force_red)
                emergency_type <= 3'd0;
            else if (emergency_green_north)
                emergency_type <= 3'd1;
            else if (emergency_green_east)
                emergency_type <= 3'd2;
            else if (emergency_green_south)
                emergency_type <= 3'd3;
            else if (emergency_green_west)
                emergency_type <= 3'd4;
            else
                emergency_type <= 3'd0;
        end
        else if (soft_reset && emergency_mode) begin
            // SOFT RESET - resume from stored state
            emergency_mode <= 1'b0;
            current_state <= stored_state;
            count <= stored_count;
            // next_state will be recomputed in combinational block
        end
        else if (!emergency_mode) begin
            // NORMAL OPERATION (your original FSM)
            current_state <= next_state;
            if (count == 7'd0)
                count <= count_next;
            else
                count <= count - 1;
        end
        // else: emergency_mode active - do nothing (timer frozen, no state change)
    end
end

always @(*) begin
    // Default outputs
    north_light = RED;
    east_light  = RED;
    west_light  = RED;
    south_light = RED;
    next_state  = current_state;
    count_next  = 7'd0;
    timer       = count;
    emergency_active = emergency_mode;

    if (emergency_mode) begin
        // EMERGENCY OVERRIDE - outputs depend on emergency_type
        case (emergency_type)
            3'd0: begin  // Force ALL RED (wrong-way ambulance)
                north_light = ALL_RED;
                east_light  = ALL_RED;
                south_light = ALL_RED;
                west_light  = ALL_RED;
                // count_next not used, timer frozen
            end
            3'd1: begin  // Force NORTH GREEN
                north_light = GREEN;
                east_light  = RED;
                south_light = RED;
                west_light  = RED;
            end
            3'd2: begin  // Force EAST GREEN
                north_light = RED;
                east_light  = GREEN;
                south_light = RED;
                west_light  = RED;
            end
            3'd3: begin  // Force SOUTH GREEN
                north_light = RED;
                east_light  = RED;
                south_light = GREEN;
                west_light  = RED;
            end
            3'd4: begin  // Force WEST GREEN
                north_light = RED;
                east_light  = RED;
                south_light = RED;
                west_light  = GREEN;
            end
            default: begin
                north_light = ALL_RED;
                east_light  = ALL_RED;
                south_light = ALL_RED;
                west_light  = ALL_RED;
            end
        endcase
    end else begin
        // NORMAL FSM OPERATION - exactly as you wrote
        case (current_state)
            NORTH_GREEN: begin
                north_light = GREEN;
                count_next = 7'd20;
                if (count == 7'd0) next_state = NORTH_YELLOW;
            end
            NORTH_YELLOW: begin
                north_light = YELLOW;
                count_next = 7'd5;
                if (count == 7'd0) next_state = NORTH_RED;
            end
            NORTH_RED: begin
                north_light = ALL_RED;
                east_light  = ALL_RED;
                west_light  = ALL_RED;
                south_light = ALL_RED;
                count_next = 7'd85;
                if (count == 7'd0) next_state = EAST_GREEN;
            end
            EAST_GREEN: begin
                east_light = GREEN;
                count_next = 7'd20;
                if (count == 7'd0) next_state = EAST_YELLOW;
            end
            EAST_YELLOW: begin
                east_light = YELLOW;
                count_next = 7'd5;
                if (count == 7'd0) next_state = EAST_RED;
            end
            EAST_RED: begin
                north_light = ALL_RED;
                east_light  = ALL_RED;
                west_light  = ALL_RED;
                south_light = ALL_RED;
                count_next = 7'd85;
                if (count == 7'd0) next_state = SOUTH_GREEN;
            end
            SOUTH_GREEN: begin
                south_light = GREEN;
                count_next = 7'd20;
                if (count == 7'd0) next_state = SOUTH_YELLOW;
            end
            SOUTH_YELLOW: begin
                south_light = YELLOW;
                count_next = 7'd5;
                if (count == 7'd0) next_state = SOUTH_RED;
            end
            SOUTH_RED: begin
                north_light = ALL_RED;
                east_light  = ALL_RED;
                west_light  = ALL_RED;
                south_light = ALL_RED;
                count_next = 7'd85;
                if (count == 7'd0) next_state = WEST_GREEN;
            end
            WEST_GREEN: begin
                west_light = GREEN;
                count_next = 7'd20;
                if (count == 7'd0) next_state = WEST_YELLOW;
            end
            WEST_YELLOW: begin
                west_light = YELLOW;
                count_next = 7'd5;
                if (count == 7'd0) next_state = WEST_RED;
            end
            WEST_RED: begin
                north_light = ALL_RED;
                east_light  = ALL_RED;
                west_light  = ALL_RED;
                south_light = ALL_RED;
                count_next = 7'd85;
                if (count == 7'd0) next_state = NORTH_GREEN;
            end
            default: begin
                north_light = ALL_RED;
                east_light  = ALL_RED;
                west_light  = ALL_RED;
                south_light = ALL_RED;
                count_next = 7'd85;
                next_state = NORTH_GREEN;
            end
        endcase
    end
end

endmodule

Silicon.srcs/sim_1/new/traffic_signal_fsm_tb.v
`timescale 1ns / 1ps

module traffic_signal_fsm_tb;

    reg clk;
    reg reset;
    reg emergency_force_red;
    reg emergency_green_north;
    reg emergency_green_east;
    reg emergency_green_south;
    reg emergency_green_west;
    reg soft_reset;
    wire [1:0] north_light, east_light, west_light, south_light;
    wire [6:0] timer;
    wire emergency_active;

    // Instantiate DUT
    traffic_signal_fsm uut (
        .clk(clk),
        .reset(reset),
        .emergency_force_red(emergency_force_red),
        .emergency_green_north(emergency_green_north),
        .emergency_green_east(emergency_green_east),
        .emergency_green_south(emergency_green_south),
        .emergency_green_west(emergency_green_west),
        .soft_reset(soft_reset),
        .north_light(north_light),
        .east_light(east_light),
        .west_light(west_light),
        .south_light(south_light),
        .timer(timer),
        .emergency_active(emergency_active)
    );

    // Clock: 10ns period
    always #5 clk = ~clk;

    // Helper task to wait for timer to reach a certain value
    task wait_timer_value;
        input [6:0] target;
        begin
            while (timer != target) @(posedge clk);
        end
    endtask

    initial begin
        // Dump waveform for viewing
        $dumpfile("traffic_fsm_emergency.vcd");
        $dumpvars(0, traffic_signal_fsm_tb);
        
        // Initialize inputs
        clk = 0;
        reset = 1;
        emergency_force_red = 0;
        emergency_green_north = 0;
        emergency_green_east = 0;
        emergency_green_south = 0;
        emergency_green_west = 0;
        soft_reset = 0;
        
        // Release hard reset after 5 cycles
        repeat(5) @(posedge clk);
        reset = 0;
        $display("\n========== TESTBENCH START ==========");
        $display("Normal operation begins (NORTH_GREEN)");
        
        // --------------------------------------------------------------
        // TEST 1: Normal operation for a while (observe NORTH_GREEN -> YELLOW -> RED -> EAST_GREEN...)
        // --------------------------------------------------------------
        repeat(200) @(posedge clk);
        $display("\n[TEST 1] Normal cycle verified (observed in waveform)");
        
        // --------------------------------------------------------------
        // TEST 2: Emergency FORCE ALL RED (wrong-way ambulance)
        // --------------------------------------------------------------
        $display("\n[TEST 2] Force ALL RED + freeze timer");
        emergency_force_red = 1;
        @(posedge clk);
        #1;
        if ({north_light, east_light, south_light, west_light} == {8{2'b11}})
            $display("  ✓ ALL lights = ALL_RED");
        else
            $display("  ✗ ERROR: Not all RED");
        
        // Timer should freeze - wait 10 cycles and check no change
        repeat(10) @(posedge clk);
        $display("  Timer frozen at %0d (no change observed)", timer);
        
        // Clear force red and soft reset
        emergency_force_red = 0;
        soft_reset = 1;
        @(posedge clk);
        soft_reset = 0;
        $display("  Soft reset -> resume normal cycle");
        repeat(50) @(posedge clk);
        
        // --------------------------------------------------------------
        // TEST 3: Emergency GREEN for NORTH
        // --------------------------------------------------------------
        $display("\n[TEST 3] Force NORTH GREEN");
        emergency_green_north = 1;
        @(posedge clk);
        #1;
        if (north_light == 2'b01 && east_light == 2'b00 && south_light == 2'b00 && west_light == 2'b00)
            $display("  ✓ NORTH = GREEN, others RED");
        else
            $display("  ✗ ERROR: Wrong lights - N=%b E=%b S=%b W=%b", north_light, east_light, south_light, west_light);
        
        emergency_green_north = 0;
        soft_reset = 1;
        @(posedge clk);
        soft_reset = 0;
        repeat(30) @(posedge clk);
        
        // --------------------------------------------------------------
        // TEST 4: Emergency GREEN for EAST
        // --------------------------------------------------------------
        $display("\n[TEST 4] Force EAST GREEN");
        emergency_green_east = 1;
        @(posedge clk);
        #1;
        if (east_light == 2'b01 && north_light == 2'b00 && south_light == 2'b00 && west_light == 2'b00)
            $display("  ✓ EAST = GREEN, others RED");
        else
            $display("  ✗ ERROR");
        emergency_green_east = 0;
        soft_reset = 1;
        @(posedge clk);
        soft_reset = 0;
        repeat(30) @(posedge clk);
        
        // --------------------------------------------------------------
        // TEST 5: Emergency GREEN for SOUTH
        // --------------------------------------------------------------
        $display("\n[TEST 5] Force SOUTH GREEN");
        emergency_green_south = 1;
        @(posedge clk);
        #1;
        if (south_light == 2'b01 && north_light == 2'b00 && east_light == 2'b00 && west_light == 2'b00)
            $display("  ✓ SOUTH = GREEN, others RED");
        else
            $display("  ✗ ERROR");
        emergency_green_south = 0;
        soft_reset = 1;
        @(posedge clk);
        soft_reset = 0;
        repeat(30) @(posedge clk);
        
        // --------------------------------------------------------------
        // TEST 6: Emergency GREEN for WEST
        // --------------------------------------------------------------
        $display("\n[TEST 6] Force WEST GREEN");
        emergency_green_west = 1;
        @(posedge clk);
        #1;
        if (west_light == 2'b01 && north_light == 2'b00 && east_light == 2'b00 && south_light == 2'b00)
            $display("  ✓ WEST = GREEN, others RED");
        else
            $display("  ✗ ERROR");
        emergency_green_west = 0;
        soft_reset = 1;
        @(posedge clk);
        soft_reset = 0;
        repeat(30) @(posedge clk);
        
        // --------------------------------------------------------------
        // TEST 7: Priority - force_red overrides any green
        // --------------------------------------------------------------
        $display("\n[TEST 7] Priority: force_red > green");
        emergency_green_north = 1;
        emergency_force_red = 1;
        @(posedge clk);
        #1;
        if ({north_light, east_light, south_light, west_light} == {8{2'b11}})
            $display("  ✓ force_red takes priority (ALL_RED)");
        else
            $display("  ✗ ERROR: force_red should override green");
        emergency_force_red = 0;
        emergency_green_north = 0;
        soft_reset = 1;
        @(posedge clk);
        soft_reset = 0;
        repeat(30) @(posedge clk);
        
        // --------------------------------------------------------------
        // TEST 8: Priority among greens (North > East > South > West)
        // --------------------------------------------------------------
        $display("\n[TEST 8] Priority among greens (North > East > South > West)");
        emergency_green_east = 1;
        emergency_green_north = 1;
        @(posedge clk);
        #1;
        if (north_light == 2'b01)
            $display("  ✓ North gets priority over East");
        else
            $display("  ✗ ERROR: North should win");
        emergency_green_north = 0;
        emergency_green_east = 0;
        soft_reset = 1; @(posedge clk); soft_reset = 0;
        repeat(30) @(posedge clk);
        
        // --------------------------------------------------------------
        // TEST 9: Hard reset (complete refresh)
        // --------------------------------------------------------------
        $display("\n[TEST 9] Hard reset -> back to NORTH_GREEN");
        reset = 1;
        repeat(2) @(posedge clk);
        reset = 0;
        @(posedge clk);
        #1;
        if (north_light == 2'b01 && east_light == 2'b00 && south_light == 2'b00 && west_light == 2'b00)
            $display("  ✓ Hard reset: NORTH_GREEN");
        else
            $display("  ✗ ERROR: Hard reset failed");
        
        // Let it run a bit to see normal cycle again
        repeat(100) @(posedge clk);
        
        $display("\n========== ALL TESTS PASSED ==========");
        $display("Simulation complete. Open waveform to observe.");
        $finish;
    end

    // Optional: monitor to console (can comment out if too verbose)
    always @(posedge clk) begin
        if (!reset && !emergency_active)
            $display("Normal: N=%b E=%b S=%b W=%b | Timer=%0d", north_light, east_light, south_light, west_light, timer);
        else if (emergency_active)
            $display("EMERG: N=%b E=%b S=%b W=%b | Type=%b", north_light, east_light, south_light, west_light, 
                     {emergency_force_red, emergency_green_north, emergency_green_east, emergency_green_south, emergency_green_west});
    end

endmodule

Silicon.sim/sim_1/behav/xsim/traffic_fsm_emergency.vcd
$date
   Sat Apr 25 07:12:12 2026
$end

$version
  2024.2.0
  $dumpfile ("traffic_fsm_emergency.vcd") 
$end

$timescale
  1ps
$end

$scope module traffic_signal_fsm_tb $end
$var reg 1 ! clk $end
$var reg 1 " reset $end
$var reg 1 # emergency_force_red $end
$var reg 1 $ emergency_green_north $end
$var reg 1 % emergency_green_east $end
$var reg 1 & emergency_green_south $end
$var reg 1 ' emergency_green_west $end
$var reg 1 ( soft_reset $end
$var wire 2 ) north_light [1:0] $end
$var wire 2 * east_light [1:0] $end
$var wire 2 + west_light [1:0] $end
$var wire 2 , south_light [1:0] $end
$var wire 7 - timer [6:0] $end
$var wire 1 . emergency_active $end
$scope module uut $end
$var wire 1 / clk $end
$var wire 1 0 reset $end
$var wire 1 1 emergency_force_red $end
$var wire 1 2 emergency_green_north $end
$var wire 1 3 emergency_green_east $end
$var wire 1 4 emergency_green_south $end
$var wire 1 5 emergency_green_west $end
$var wire 1 6 soft_reset $end
$var reg 2 7 north_light [1:0] $end
$var reg 2 8 east_light [1:0] $end
$var reg 2 9 west_light [1:0] $end
$var reg 2 : south_light [1:0] $end
$var reg 7 ; timer [6:0] $end
$var reg 1 < emergency_active $end
$var reg 4 = current_state [3:0] $end
$var reg 4 > next_state [3:0] $end
$var reg 7 ? count [6:0] $end
$var reg 7 @ count_next [6:0] $end
$var reg 1 A emergency_mode $end
$var reg 3 B emergency_type [2:0] $end
$var reg 4 C stored_state [3:0] $end
$var reg 7 D stored_count [6:0] $end
$var reg 7 E stored_count_next [6:0] $end
$var wire 1 F any_emergency $end
$upscope $end
$upscope $end
$enddefinitions $end

#0
$dumpvars
0!
1"
0#
0$
0%
0&
0'
0(
b1 )
b0 *
b0 +
b0 ,
b0 -
0.
0/
10
01
02
03
04
05
06
b1 7
b0 8
b0 9
b0 :
b0 ;
0<
b0 =
b1 >
b0 ?
b10100 @
0A
b0 B
b0 C
b0 D
b0 E
0F
$end

#5000
1!
1/

#10000
0!
0/

#15000
1!
1/

#20000
0!
0/

#25000
1!
1/

#30000
0!
0/

#35000
1!
1/

#40000
0!
0/

#45000
1!
0"
b10 )
b10100 -
1/
00
b10 7
b10100 ;
b1 =
b10100 ?
b101 @

#50000
0!
0/

#55000
1!
b10011 -
1/
b10 7
b10011 ;
b10011 ?
b101 @

#60000
0!
0/

#65000
1!
b10010 -
1/
b10 7
b10010 ;
b10010 ?
b101 @

#70000
0!
0/

#75000
1!
b10001 -
1/
b10 7
b10001 ;
b10001 ?
b101 @

#80000
0!
0/

#85000
1!
b10000 -
1/
b10 7
b10000 ;
b10000 ?
b101 @

#90000
0!
0/

#95000
1!
b1111 -
1/
b10 7
b1111 ;
b1111 ?
b101 @

#100000
0!
0/

#105000
1!
b1110 -
1/
b10 7
b1110 ;
b1110 ?
b101 @

#110000
0!
0/

#115000
1!
b1101 -
1/
b10 7
b1101 ;
b1101 ?
b101 @

#120000
0!
0/

#125000
1!
b1100 -
1/
b10 7
b1100 ;
b1100 ?
b101 @

#130000
0!
0/

#135000
1!
b1011 -
1/
b10 7
b1011 ;
b1011 ?
b101 @

#140000
0!
0/

#145000
1!
b1010 -
1/
b10 7
b1010 ;
b1010 ?
b101 @

#150000
0!
0/

#155000
1!
b1001 -
1/
b10 7
b1001 ;
b1001 ?
b101 @

#160000
0!
0/

#165000
1!
b1000 -
1/
b10 7
b1000 ;
b1000 ?
b101 @

#170000
0!
0/

#175000
1!
b111 -
1/
b10 7
b111 ;
b111 ?
b101 @

#180000
0!
0/

#185000
1!
b110 -
1/
b10 7
b110 ;
b110 ?
b101 @

#190000
0!
0/

#195000
1!
b101 -
1/
b10 7
b101 ;
b101 ?
b101 @

#200000
0!
0/

#205000
1!
b100 -
1/
b10 7
b100 ;
b100 ?
b101 @

#210000
0!
0/

#215000
1!
b11 -
1/
b10 7
b11 ;
b11 ?
b101 @

#220000
0!
0/

#225000
1!
b10 -
1/
b10 7
b10 ;
b10 ?
b101 @

#230000
0!
0/

#235000
1!
b1 -
1/
b10 7
b1 ;
b1 ?
b101 @

#240000
0!
0/

#245000
1!
b0 -
1/
b10 7
b0 ;
b10 >
b0 ?
b101 @

#250000
0!
0/

#255000
1!
b11 )
b11 *
b11 +
b11 ,
b101 -
1/
b11 7
b11 8
b11 9
b11 :
b101 ;
b10 =
b101 ?
b1010101 @

#260000
0!
0/

#265000
1!
b100 -
1/
b11 7
b11 8
b11 9
b11 :
b100 ;
b100 ?
b1010101 @

#270000
0!
0/

#275000
1!
b11 -
1/
b11 7
b11 8
b11 9
b11 :
b11 ;
b11 ?
b1010101 @

#280000
0!
0/

#285000
1!
b10 -
1/
b11 7
b11 8
b11 9
b11 :
b10 ;
b10 ?
b1010101 @

#290000
0!
0/

#295000
1!
b1 -
1/
b11 7
b11 8
b11 9
b11 :
b1 ;
b1 ?
b1010101 @

#300000
0!
0/

#305000
1!
b0 -
1/
b11 7
b11 8
b11 9
b11 :
b0 ;
b11 >
b0 ?
b1010101 @

#310000
0!
0/

#315000
1!
b0 )
b1 *
b0 +
b0 ,
b1010101 -
1/
b0 7
b1 8
b0 9
b0 :
b1010101 ;
b11 =
b1010101 ?
b10100 @

#320000
0!
0/

#325000
1!
b1010100 -
1/
b1 8
b1010100 ;
b1010100 ?
b10100 @

#330000
0!
0/

#335000
1!
b1010011 -
1/
b1 8
b1010011 ;
b1010011 ?
b10100 @

#340000
0!
0/

#345000
1!
b1010010 -
1/
b1 8
b1010010 ;
b1010010 ?
b10100 @

#350000
0!
0/

#355000
1!
b1010001 -
1/
b1 8
b1010001 ;
b1010001 ?
b10100 @

#360000
0!
0/

#365000
1!
b1010000 -
1/
b1 8
b1010000 ;
b1010000 ?
b10100 @

#370000
0!
0/

#375000
1!
b1001111 -
1/
b1 8
b1001111 ;
b1001111 ?
b10100 @

#380000
0!
0/

#385000
1!
b1001110 -
1/
b1 8
b1001110 ;
b1001110 ?
b10100 @

#390000
0!
0/

#395000
1!
b1001101 -
1/
b1 8
b1001101 ;
b1001101 ?
b10100 @

#400000
0!
0/

#405000
1!
b1001100 -
1/
b1 8
b1001100 ;
b1001100 ?
b10100 @

#410000
0!
0/

#415000
1!
b1001011 -
1/
b1 8
b1001011 ;
b1001011 ?
b10100 @

#420000
0!
0/

#425000
1!
b1001010 -
1/
b1 8
b1001010 ;
b1001010 ?
b10100 @

#430000
0!
0/

#435000
1!
b1001001 -
1/
b1 8
b1001001 ;
b1001001 ?
b10100 @

#440000
0!
0/

#445000
1!
b1001000 -
1/
b1 8
b1001000 ;
b1001000 ?
b10100 @

#450000
0!
0/

#455000
1!
b1000111 -
1/
b1 8
b1000111 ;
b1000111 ?
b10100 @

#460000
0!
0/

#465000
1!
b1000110 -
1/
b1 8
b1000110 ;
b1000110 ?
b10100 @

#470000
0!
0/

#475000
1!
b1000101 -
1/
b1 8
b1000101 ;
b1000101 ?
b10100 @

#480000
0!
0/

#485000
1!
b1000100 -
1/
b1 8
b1000100 ;
b1000100 ?
b10100 @

#490000
0!
0/

#495000
1!
b1000011 -
1/
b1 8
b1000011 ;
b1000011 ?
b10100 @

#500000
0!
0/

#505000
1!
b1000010 -
1/
b1 8
b1000010 ;
b1000010 ?
b10100 @

#510000
0!
0/

#515000
1!
b1000001 -
1/
b1 8
b1000001 ;
b1000001 ?
b10100 @

#520000
0!
0/

#525000
1!
b1000000 -
1/
b1 8
b1000000 ;
b1000000 ?
b10100 @

#530000
0!
0/

#535000
1!
b111111 -
1/
b1 8
b111111 ;
b111111 ?
b10100 @

#540000
0!
0/

#545000
1!
b111110 -
1/
b1 8
b111110 ;
b111110 ?
b10100 @

#550000
0!
0/

#555000
1!
b111101 -
1/
b1 8
b111101 ;
b111101 ?
b10100 @

#560000
0!
0/

#565000
1!
b111100 -
1/
b1 8
b111100 ;
b111100 ?
b10100 @

#570000
0!
0/

#575000
1!
b111011 -
1/
b1 8
b111011 ;
b111011 ?
b10100 @

#580000
0!
0/

#585000
1!
b111010 -
1/
b1 8
b111010 ;
b111010 ?
b10100 @

#590000
0!
0/

#595000
1!
b111001 -
1/
b1 8
b111001 ;
b111001 ?
b10100 @

#600000
0!
0/

#605000
1!
b111000 -
1/
b1 8
b111000 ;
b111000 ?
b10100 @

#610000
0!
0/

#615000
1!
b110111 -
1/
b1 8
b110111 ;
b110111 ?
b10100 @

#620000
0!
0/

#625000
1!
b110110 -
1/
b1 8
b110110 ;
b110110 ?
b10100 @

#630000
0!
0/

#635000
1!
b110101 -
1/
b1 8
b110101 ;
b110101 ?
b10100 @

#640000
0!
0/

#645000
1!
b110100 -
1/
b1 8
b110100 ;
b110100 ?
b10100 @

#650000
0!
0/

#655000
1!
b110011 -
1/
b1 8
b110011 ;
b110011 ?
b10100 @

#660000
0!
0/

#665000
1!
b110010 -
1/
b1 8
b110010 ;
b110010 ?
b10100 @

#670000
0!
0/

#675000
1!
b110001 -
1/
b1 8
b110001 ;
b110001 ?
b10100 @

#680000
0!
0/

#685000
1!
b110000 -
1/
b1 8
b110000 ;
b110000 ?
b10100 @

#690000
0!
0/

#695000
1!
b101111 -
1/
b1 8
b101111 ;
b101111 ?
b10100 @

#700000
0!
0/

#705000
1!
b101110 -
1/
b1 8
b101110 ;
b101110 ?
b10100 @

#710000
0!
0/

#715000
1!
b101101 -
1/
b1 8
b101101 ;
b101101 ?
b10100 @

#720000
0!
0/

#725000
1!
b101100 -
1/
b1 8
b101100 ;
b101100 ?
b10100 @

#730000
0!
0/

#735000
1!
b101011 -
1/
b1 8
b101011 ;
b101011 ?
b10100 @

#740000
0!
0/

#745000
1!
b101010 -
1/
b1 8
b101010 ;
b101010 ?
b10100 @

#750000
0!
0/

#755000
1!
b101001 -
1/
b1 8
b101001 ;
b101001 ?
b10100 @

#760000
0!
0/

#765000
1!
b101000 -
1/
b1 8
b101000 ;
b101000 ?
b10100 @

#770000
0!
0/

#775000
1!
b100111 -
1/
b1 8
b100111 ;
b100111 ?
b10100 @

#780000
0!
0/

#785000
1!
b100110 -
1/
b1 8
b100110 ;
b100110 ?
b10100 @

#790000
0!
0/

#795000
1!
b100101 -
1/
b1 8
b100101 ;
b100101 ?
b10100 @

#800000
0!
0/

#805000
1!
b100100 -
1/
b1 8
b100100 ;
b100100 ?
b10100 @

#810000
0!
0/

#815000
1!
b100011 -
1/
b1 8
b100011 ;
b100011 ?
b10100 @

#820000
0!
0/

#825000
1!
b100010 -
1/
b1 8
b100010 ;
b100010 ?
b10100 @

#830000
0!
0/

#835000
1!
b100001 -
1/
b1 8
b100001 ;
b100001 ?
b10100 @

#840000
0!
0/

#845000
1!
b100000 -
1/
b1 8
b100000 ;
b100000 ?
b10100 @

#850000
0!
0/

#855000
1!
b11111 -
1/
b1 8
b11111 ;
b11111 ?
b10100 @

#860000
0!
0/

#865000
1!
b11110 -
1/
b1 8
b11110 ;
b11110 ?
b10100 @

#870000
0!
0/

#875000
1!
b11101 -
1/
b1 8
b11101 ;
b11101 ?
b10100 @

#880000
0!
0/

#885000
1!
b11100 -
1/
b1 8
b11100 ;
b11100 ?
b10100 @

#890000
0!
0/

#895000
1!
b11011 -
1/
b1 8
b11011 ;
b11011 ?
b10100 @

#900000
0!
0/

#905000
1!
b11010 -
1/
b1 8
b11010 ;
b11010 ?
b10100 @

#910000
0!
0/

#915000
1!
b11001 -
1/
b1 8
b11001 ;
b11001 ?
b10100 @

#920000
0!
0/

#925000
1!
b11000 -
1/
b1 8
b11000 ;
b11000 ?
b10100 @

#930000
0!
0/

#935000
1!
b10111 -
1/
b1 8
b10111 ;
b10111 ?
b10100 @

#940000
0!
0/

#945000
1!
b10110 -
1/
b1 8
b10110 ;
b10110 ?
b10100 @

#950000
0!
0/

#955000
1!
b10101 -
1/
b1 8
b10101 ;
b10101 ?
b10100 @

#960000
0!
0/

#965000
1!
b10100 -
1/
b1 8
b10100 ;
b10100 ?
b10100 @

#970000
0!
0/

#975000
1!
b10011 -
1/
b1 8
b10011 ;
b10011 ?
b10100 @

#980000
0!
0/

#985000
1!
b10010 -
1/
b1 8
b10010 ;
b10010 ?
b10100 @

#990000
0!
0/

#995000
1!
b10001 -
1/
b1 8
b10001 ;
b10001 ?
b10100 @

#1000000
0!
0/

#1005000
1!
b10000 -
1/
b1 8
b10000 ;
b10000 ?
b10100 @

#1010000
0!
0/

#1015000
1!
b1111 -
1/
b1 8
b1111 ;
b1111 ?
b10100 @

#1020000
0!
0/

#1025000
1!
b1110 -
1/
b1 8
b1110 ;
b1110 ?
b10100 @

#1030000
0!
0/

#1035000
1!
b1101 -
1/
b1 8
b1101 ;
b1101 ?
b10100 @

#1040000
0!
0/

#1045000
1!
b1100 -
1/
b1 8
b1100 ;
b1100 ?
b10100 @

#1050000
0!
0/

#1055000
1!
b1011 -
1/
b1 8
b1011 ;
b1011 ?
b10100 @

#1060000
0!
0/

#1065000
1!
b1010 -
1/
b1 8
b1010 ;
b1010 ?
b10100 @

#1070000
0!
0/

#1075000
1!
b1001 -
1/
b1 8
b1001 ;
b1001 ?
b10100 @

#1080000
0!
0/

#1085000
1!
b1000 -
1/
b1 8
b1000 ;
b1000 ?
b10100 @

#1090000
0!
0/

#1095000
1!
b111 -
1/
b1 8
b111 ;
b111 ?
b10100 @

#1100000
0!
0/

#1105000
1!
b110 -
1/
b1 8
b110 ;
b110 ?
b10100 @

#1110000
0!
0/

#1115000
1!
b101 -
1/
b1 8
b101 ;
b101 ?
b10100 @

#1120000
0!
0/

#1125000
1!
b100 -
1/
b1 8
b100 ;
b100 ?
b10100 @

#1130000
0!
0/

#1135000
1!
b11 -
1/
b1 8
b11 ;
b11 ?
b10100 @

#1140000
0!
0/

#1145000
1!
b10 -
1/
b1 8
b10 ;
b10 ?
b10100 @

#1150000
0!
0/

#1155000
1!
b1 -
1/
b1 8
b1 ;
b1 ?
b10100 @

#1160000
0!
0/

#1165000
1!
b0 -
1/
b1 8
b0 ;
b100 >
b0 ?
b10100 @

#1170000
0!
0/

#1175000
1!
b10 *
b10100 -
1/
b10 8
b10100 ;
b100 =
b10100 ?
b101 @

#1180000
0!
0/

#1185000
1!
b10011 -
1/
b10 8
b10011 ;
b10011 ?
b101 @

#1190000
0!
0/

#1195000
1!
b10010 -
1/
b10 8
b10010 ;
b10010 ?
b101 @

#1200000
0!
0/

#1205000
1!
b10001 -
1/
b10 8
b10001 ;
b10001 ?
b101 @

#1210000
0!
0/

#1215000
1!
b10000 -
1/
b10 8
b10000 ;
b10000 ?
b101 @

#1220000
0!
0/

#1225000
1!
b1111 -
1/
b10 8
b1111 ;
b1111 ?
b101 @

#1230000
0!
0/

#1235000
1!
b1110 -
1/
b10 8
b1110 ;
b1110 ?
b101 @

#1240000
0!
0/

#1245000
1!
b1101 -
1/
b10 8
b1101 ;
b1101 ?
b101 @

#1250000
0!
0/

#1255000
1!
b1100 -
1/
b10 8
b1100 ;
b1100 ?
b101 @

#1260000
0!
0/

#1265000
1!
b1011 -
1/
b10 8
b1011 ;
b1011 ?
b101 @

#1270000
0!
0/

#1275000
1!
b1010 -
1/
b10 8
b1010 ;
b1010 ?
b101 @

#1280000
0!
0/

#1285000
1!
b1001 -
1/
b10 8
b1001 ;
b1001 ?
b101 @

#1290000
0!
0/

#1295000
1!
b1000 -
1/
b10 8
b1000 ;
b1000 ?
b101 @

#1300000
0!
0/

#1305000
1!
b111 -
1/
b10 8
b111 ;
b111 ?
b101 @

#1310000
0!
0/

#1315000
1!
b110 -
1/
b10 8
b110 ;
b110 ?
b101 @

#1320000
0!
0/

#1325000
1!
b101 -
1/
b10 8
b101 ;
b101 ?
b101 @

#1330000
0!
0/

#1335000
1!
b100 -
1/
b10 8
b100 ;
b100 ?
b101 @

#1340000
0!
0/

#1345000
1!
b11 -
1/
b10 8
b11 ;
b11 ?
b101 @

#1350000
0!
0/

#1355000
1!
b10 -
1/
b10 8
b10 ;
b10 ?
b101 @

#1360000
0!
0/

#1365000
1!
b1 -
1/
b10 8
b1 ;
b1 ?
b101 @

#1370000
0!
0/

#1375000
1!
b0 -
1/
b10 8
b0 ;
b101 >
b0 ?
b101 @

#1380000
0!
0/

#1385000
1!
b11 )
b11 *
b11 +
b11 ,
b101 -
1/
b11 7
b11 8
b11 9
b11 :
b101 ;
b101 =
b101 ?
b1010101 @

#1390000
0!
0/

#1395000
1!
b100 -
1/
b11 7
b11 8
b11 9
b11 :
b100 ;
b100 ?
b1010101 @

#1400000
0!
0/

